ssh_copy_id_windows/__init__.py
ssh_copy_id_windows/__main__.py
ssh_copy_id_windows/app.py
ssh_copy_id_windows/backend/__init__.py
ssh_copy_id_windows/backend/copy_id.py
ssh_copy_id_windows/backend/ssh_integration/__init__.py
ssh_copy_id_windows/backend/ssh_integration/ssh.py
ssh_copy_id_windows-2.0.0.dist-info/entry_points.txt
ssh_copy_id_windows-2.0.0.dist-info/LICENSE
ssh_copy_id_windows-2.0.0.dist-info/METADATA
ssh_copy_id_windows-2.0.0.dist-info/WHEEL
ssh_copy_id_windows-2.0.0.dist-info/RECORD
