Metadata-Version: 2.3
Name: ssh-copy-id-windows
Version: 2.0.0
Summary: ssh-copy-id for Windows OS.
License: Apache License
Keywords: ssh-copy-id,ssh,ssh-copy-id-windows,python,exe,ssh-windows,windows
Author: overgodofchaos
Author-email: vezonzzzzzz@gmail.com
Requires-Python: >=3.10,<4.0
Classifier: License :: Other/Proprietary License
Classifier: Programming Language :: Python :: 3
Classifier: Programming Language :: Python :: 3.10
Classifier: Programming Language :: Python :: 3.11
Classifier: Programming Language :: Python :: 3.12
Classifier: Programming Language :: Python :: 3.13
Requires-Dist: fabric (>=3.2.2,<4.0.0)
Requires-Dist: loguru (>=0.7.3,<0.8.0)
Requires-Dist: typer (>=0.19.2,<0.20.0)
